{
  "metadata": {
    "processed_date": "2025-12-26T19:10:16.686672",
    "total_intents": 13,
    "total_patterns": 768,
    "total_responses": 26,
    "quality_metrics": {
      "total_intents": 13,
      "total_patterns": 768,
      "total_responses": 26,
      "avg_patterns_per_intent": 59.07692307692308,
      "avg_responses_per_intent": 2.0,
      "class_balance_score": 0.84375,
      "data_quality_score": 0,
      "avg_pattern_length": 23.686197916666668,
      "avg_response_length": 126.65384615384616,
      "unique_words": 865,
      "processing_timestamp": "2025-12-26T19:10:16.686658"
    }
  },
  "intents": [
    {
      "tag": "pandemi_covid19",
      "original_patterns_count": 54,
      "processed_patterns_count": 54,
      "patterns_cleaned": [
        "kebijakan kuliah selama pandemi",
        "apakah kuliah online atau offline",
        "protokol kesehatan di kampus",
        "vaksinasi untuk mahasiswa",
        "kuliah hybrid bagaimana",
        "sistem pembelajaran jarak jauh",
        "apakah wajib vaksin untuk masuk kampus",
        "tes covid di kampus",
        "isolasi mandiri bagi mahasiswa terkonfirmasi covid",
        "bantuan untuk mahasiswa terdampak covid",
        "kebijakan absensi selama pandemi",
        "ujian online selama pandemi",
        "laboratorium online selama pandemi",
        "praktikum bagaimana saat pandemi",
        "skripsi selama pandemi",
        "bimbingan online dengan dosen",
        "perpustakaan online",
        "layanan konseling selama pandemi",
        "beasiswa khusus pandemi",
        "keringanan biaya selama pandemi",
        "penangguhan studi karena pandemi",
        "kembali ke kampus setelah pandemi",
        "new normal di kampus",
        "pembatasan kapasitas ruangan",
        "sertifikat vaksin untuk akses kampus",
        "rapid test di kampus",
        "hotline covid kampus",
        "kantin selama pandemi",
        "transportasi kampus selama pandemi",
        "asrama selama pandemi",
        "kegiatan organisasi selama pandemi",
        "wisuda selama pandemi",
        "penerimaan mahasiswa baru selama pandemi",
        "pertukaran pelajar selama pandemi",
        "konferensi online",
        "penelitian tentang covid 19",
        "relawan covid di kampus",
        "donasi untuk penanganan covid",
        "edukasi pencegahan covid",
        "satgas covid kampus",
        "aplikasi tracing kampus",
        "laporan kasus covid di kampus",
        "kerjasama dengan rumah sakit",
        "pcr test untuk mahasiswa",
        "asuransi kesehatan covid",
        "kebijakan masker di kampus",
        "sanitizer tersedia di mana saja",
        "ventilasi ruangan kelas",
        "sirkulasi udara di gedung",
        "makan di kantin boleh buka masker",
        "olahraga di kampus selama pandemi",
        "gym buka selama pandemi",
        "layanan kesehatan mental selama pandemi",
        "stress karena pandemi"
      ],
      "responses": [
        "selama pandemi kampus menerapkan sistem hybrid 60 online 40 offline dengan protokol ketat vaksinasi wajib untuk akses kampus",
        "untuk informasi terkini tentang kebijakan pandemi kunjungi covid19 univ ac id atau hubungi hotline 1500 123"
      ],
      "context": [
        "situasi_khusus"
      ],
      "entities": [],
      "follow_up": []
    },
    {
      "tag": "kelas_internasional",
      "original_patterns_count": 56,
      "processed_patterns_count": 56,
      "patterns_cleaned": [
        "program kelas internasional",
        "international class",
        "kuliah bahasa inggris",
        "program double degree",
        "kurikulum internasional",
        "kerjasama dengan universitas luar",
        "kelas dengan pengajar asing",
        "sertifikat internasional",
        "akreditasi internasional",
        "program twinning",
        "credit transfer ke luar negeri",
        "kelas malam untuk pekerja",
        "executive class",
        "weekend class",
        "online international program",
        "micro credential",
        "professional certification program",
        "executive mba",
        "global leadership program",
        "cross cultural learning",
        "international immersion program",
        "study tour ke luar negeri",
        "global case competition",
        "international internship",
        "global virtual team project",
        "international research collaboration",
        "joint publication",
        "international conference funding",
        "bahasa pengantar inggris",
        "toefl requirement for international class",
        "ielts minimum score",
        "interview for international program",
        "biaya kelas internasional",
        "scholarship for international class",
        "visa support for international students",
        "host family program",
        "buddy program for international students",
        "cross cultural workshop",
        "international student association",
        "global alumni network",
        "career opportunity international",
        "multinational company recruitment",
        "global competency certificate",
        "intercultural communication skill",
        "diversity and inclusion training",
        "global citizenship program",
        "sustainable development goals course",
        "united nations model",
        "international law program",
        "global health program",
        "international business program",
        "global engineering program",
        "international relations",
        "diplomacy program",
        "foreign policy analysis",
        "global governance"
      ],
      "responses": [
        "kami menyelenggarakan 15 program kelas internasional dengan pengantar bahasa inggris persyaratan toefl 550 ielts 6 0 ipk min 3 0",
        "program double degree tersedia dengan partner di usa australia jepang dan eropa info lengkap di international univ ac id"
      ],
      "context": [
        "program_khusus"
      ],
      "entities": [
        "bahasa_pengantar",
        "partner_universitas",
        "biaya",
        "persyaratan"
      ],
      "follow_up": []
    },
    {
      "tag": "inkubasi_startup",
      "original_patterns_count": 60,
      "processed_patterns_count": 60,
      "patterns_cleaned": [
        "program inkubasi startup",
        "business incubator kampus",
        "pendanaan untuk startup mahasiswa",
        "kompetisi bisnis mahasiswa",
        "workshop entrepreneurship",
        "mentor bisnis dari industri",
        "co working space untuk startup",
        "prototype funding",
        "patent assistance for student invention",
        "technology commercialization",
        "angel investor network",
        "venture capital connection",
        "pitching competition",
        "business plan competition",
        "startup weekend",
        "hackathon for social innovation",
        "design thinking for business",
        "lean startup workshop",
        "minimum viable product guidance",
        "market validation support",
        "legal advice for startup",
        "tax consultation for new business",
        "intellectual property rights",
        "trademark registration help",
        "company registration assistance",
        "business license guidance",
        "accounting for startups",
        "financial projection workshop",
        "funding pitch preparation",
        "investor meeting simulation",
        "networking with alumni entrepreneurs",
        "industry partnership for startup",
        "market entry strategy",
        "digital marketing for startup",
        "e commerce setup help",
        "social media for business",
        "export import for startup",
        "global market access",
        "sustainability business model",
        "social entrepreneurship",
        "tech startup support",
        "biotech startup incubator",
        "edtech innovation",
        "fintech laboratory",
        "healthtech development",
        "agritech program",
        "smart city innovation",
        "green technology startup",
        "women entrepreneurship program",
        "student entrepreneur award",
        "alumni investment fund",
        "university venture fund",
        "equity free grant for startup",
        "pre seed funding",
        "seed funding opportunity",
        "series a preparation",
        "exit strategy workshop",
        "startup acquisition guidance",
        "ipo preparation for university spin off",
        "licensing technology from university"
      ],
      "responses": [
        "kampus memiliki inkubator bisnis dengan fasilitas co working space mentor industri pendanaan awal hingga rp 100 juta dan akses jaringan investor",
        "program inkubasi 6 bulan dengan workshop mingguan mentoring 1 on 1 dan demo day di akhir program pendaftaran dibuka setiap semester"
      ],
      "context": [
        "kewirausahaan"
      ],
      "entities": [],
      "follow_up": [
        "pendaftaran_inkubator",
        "contoh_startup_sukses"
      ]
    },
    {
      "tag": "sertifikasi_mikro",
      "original_patterns_count": 64,
      "processed_patterns_count": 64,
      "patterns_cleaned": [
        "micro credential program",
        "sertifikat profesional singkat",
        "badge digital untuk skill",
        "short course dengan sertifikat",
        "online certificate program",
        "professional development course",
        "upskill course for working professional",
        "reskill program",
        "digital badge from university",
        "stackable certificate",
        "continuing education unit",
        "lifelong learning program",
        "executive education",
        "corporate training program",
        "customized training for company",
        "in house training",
        "workforce development program",
        "industry recognized certificate",
        "google certificate program",
        "microsoft certification",
        "aws training",
        "cisco networking academy",
        "data analytics certificate",
        "digital marketing certificate",
        "project management certificate",
        "human resources certificate",
        "supply chain management certificate",
        "leadership certificate",
        "communication skill certificate",
        "critical thinking certificate",
        "problem solving certificate",
        "innovation certificate",
        "design thinking certificate",
        "agile methodology certificate",
        "scrum master certification",
        "product management certificate",
        "ux ui design certificate",
        "frontend development certificate",
        "backend development certificate",
        "full stack developer certificate",
        "cybersecurity certificate",
        "cloud computing certificate",
        "ai and machine learning certificate",
        "blockchain certificate",
        "iot certificate",
        "robotics certificate",
        "biotechnology certificate",
        "renewable energy certificate",
        "sustainability certificate",
        "corporate social responsibility certificate",
        "risk management certificate",
        "financial planning certificate",
        "entrepreneurship certificate",
        "social media marketing certificate",
        "content creation certificate",
        "video production certificate",
        "graphic design certificate",
        "photography certificate",
        "language proficiency certificate",
        "translation certificate",
        "teaching certificate",
        "research methodology certificate",
        "academic writing certificate",
        "publication ethics certificate"
      ],
      "responses": [
        "kami menawarkan 50 program micro credential dengan sertifikat digital yang diakui industri durasi 2 12 minggu fleksibel untuk pekerja",
        "digital badge dari kampus dapat ditampilkan di linkedin dan diakui oleh perusahaan partner biaya mulai rp 500 000 rp 5 000 000"
      ],
      "context": [
        "pengembangan_skill"
      ],
      "entities": [
        "durasi",
        "biaya",
        "pengakuan",
        "format"
      ],
      "follow_up": []
    },
    {
      "tag": "layanan_alumni",
      "original_patterns_count": 60,
      "processed_patterns_count": 60,
      "patterns_cleaned": [
        "layanan untuk alumni",
        "alumni network",
        "career support for alumni",
        "email alumni",
        "library access for alumni",
        "continuing education for alumni",
        "alumni discount for further study",
        "alumni mentorship program",
        "alumni giving",
        "donasi untuk almamater",
        "alumni chapter",
        "alumni reunion",
        "homecoming event",
        "alumni directory",
        "alumni success story",
        "alumni achievement award",
        "alumni in leadership position",
        "alumni entrepreneur network",
        "alumni investment club",
        "alumni research collaboration",
        "alumni teaching opportunity",
        "guest lecture by alumni",
        "alumni scholarship fund",
        "alumni sponsored research",
        "alumni internship for current students",
        "alumni job posting",
        "alumni company visit",
        "alumni recruitment",
        "alumni mentorship for students",
        "alumni advisory board",
        "alumni feedback for curriculum",
        "alumni survey",
        "alumni newsletter",
        "alumni magazine",
        "alumni social media group",
        "alumni linkedin group",
        "alumni whatsapp group",
        "alumni regional gathering",
        "alumni international chapter",
        "alumni in government",
        "alumni in industry",
        "alumni in academia",
        "alumni startup founder",
        "alumni investor",
        "alumni policy maker",
        "alumni thought leader",
        "alumni book author",
        "alumni patent holder",
        "alumni award recipient",
        "alumni hall of fame",
        "alumni legacy",
        "alumni impact story",
        "alumni volunteer opportunity",
        "alumni ambassador program",
        "alumni referral program",
        "alumni benefits package",
        "alumni credit card",
        "alumni insurance",
        "alumni travel program",
        "alumni family program"
      ],
      "responses": [
        "alumni mendapatkan akses email seumur hidup diskon 30 untuk program s2 s3 akses perpustakaan terbatas dan jaringan 50 000 alumni",
        "bergabunglah dengan asosiasi alumni untuk networking mentorship dan peluang karir kontak"
      ],
      "context": [
        "jaringan"
      ],
      "entities": [],
      "follow_up": [
        "keanggotaan_alumni",
        "kontribusi_alumni"
      ]
    },
    {
      "tag": "riset_terapan",
      "original_patterns_count": 58,
      "processed_patterns_count": 58,
      "patterns_cleaned": [
        "penelitian terapan",
        "applied research",
        "collaboration with industry for research",
        "contract research",
        "consultancy service by faculty",
        "technology transfer",
        "commercialization of research result",
        "university spin off company",
        "patent from university research",
        "licensing university technology",
        "industry sponsored research",
        "government funded research",
        "international research grant",
        "research for community development",
        "action research",
        "participatory research",
        "community based research",
        "research for policy making",
        "evidence based policy research",
        "think tank at university",
        "policy brief publication",
        "white paper from research",
        "research impact assessment",
        "social impact of research",
        "economic impact of university research",
        "environmental impact research",
        "health impact research",
        "education impact research",
        "technology impact assessment",
        "innovation ecosystem research",
        "startup ecosystem research",
        "entrepreneurship research",
        "sustainability research",
        "climate change research",
        "renewable energy research",
        "smart city research",
        "artificial intelligence research",
        "biotechnology research",
        "nanotechnology research",
        "material science research",
        "pharmaceutical research",
        "medical device research",
        "agricultural research",
        "marine research",
        "space research",
        "defense research",
        "social science research",
        "humanities research",
        "arts research",
        "design research",
        "architecture research",
        "urban planning research",
        "law research",
        "economics research",
        "business research",
        "management research",
        "psychology research",
        "education research"
      ],
      "responses": [
        "kampus memiliki 20 pusat penelitian terapan yang bekerjasama dengan 500 perusahaan dan pemerintah dana penelitian tersedia hingga rp 5 miliar per proyek",
        "untuk kerjasama penelitian terapan hubungi research and innovation office di"
      ],
      "context": [
        "penelitian"
      ],
      "entities": [
        "pusat_riset",
        "mitra_industri",
        "pendanaan",
        "output"
      ],
      "follow_up": []
    },
    {
      "tag": "pengabdian_masyarakat",
      "original_patterns_count": 58,
      "processed_patterns_count": 58,
      "patterns_cleaned": [
        "pengabdian masyarakat",
        "community service",
        "kuliah kerja nyata kkn",
        "student volunteer program",
        "community development project",
        "social responsibility program",
        "university outreach program",
        "rural development project",
        "urban community project",
        "disaster response team",
        "health service for community",
        "legal aid clinic",
        "educational program for underprivileged",
        "literacy program",
        "digital literacy program",
        "financial literacy program",
        "environmental conservation program",
        "clean water project",
        "sanitation project",
        "renewable energy for village",
        "agricultural extension program",
        "fishery development program",
        "livestock development program",
        "micro enterprise development",
        "women empowerment program",
        "youth development program",
        "elderly care program",
        "disability support program",
        "refugee support program",
        "marginalized community support",
        "indigenous community program",
        "remote area development",
        "border area development",
        "island community development",
        "coastal community development",
        "mountain community development",
        "post disaster reconstruction",
        "covid 19 community support",
        "vaccination drive for community",
        "health screening program",
        "mental health support for community",
        "nutrition program",
        "sports development in community",
        "arts and culture program",
        "heritage conservation",
        "traditional knowledge preservation",
        "community based tourism",
        "local product development",
        "market access for community product",
        "fair trade program",
        "social entrepreneurship for community",
        "cooperative development",
        "community leadership training",
        "conflict resolution training",
        "peace building program",
        "interfaith dialogue program",
        "cross cultural understanding program",
        "global citizenship program"
      ],
      "responses": [
        "mahasiswa wajib mengikuti kkn selama 2 bulan di semester 6 tersedia 100 lokasi di seluruh indonesia dengan fokus berbeda beda",
        "program pengabdian masyarakat mencakup edukasi kesehatan ekonomi dan lingkungan mahasiswa dapat memproyekkan sesuai minat"
      ],
      "context": [
        "tridharma"
      ],
      "entities": [],
      "follow_up": [
        "pendaftaran_kkn",
        "contoh_proyek"
      ]
    },
    {
      "tag": "fasilitas_digital",
      "original_patterns_count": 62,
      "processed_patterns_count": 62,
      "patterns_cleaned": [
        "fasilitas digital kampus",
        "digital campus",
        "campus wifi coverage",
        "internet speed in campus",
        "e learning platform",
        "learning management system",
        "online library access",
        "digital repository",
        "research data management system",
        "high performance computing",
        "cloud computing for research",
        "big data infrastructure",
        "ai computing cluster",
        "vr ar laboratory",
        "3d printing facility",
        "digital fabrication lab",
        "maker space",
        "innovation lab",
        "digital studio",
        "recording studio",
        "broadcasting studio",
        "podcast studio",
        "video conferencing facility",
        "smart classroom",
        "interactive whiteboard",
        "digital signage",
        "campus mobile app",
        "student portal",
        "digital payment system",
        "cashless campus",
        "smart id card",
        "nfc access system",
        "attendance system with facial recognition",
        "parking management system",
        "energy management system",
        "building management system",
        "iot infrastructure",
        "sensor network in campus",
        "environmental monitoring system",
        "air quality monitoring",
        "water quality monitoring",
        "waste management system",
        "smart lighting",
        "solar panel monitoring",
        "electric vehicle charging station",
        "bike sharing system",
        "campus navigation app",
        "indoor positioning system",
        "emergency alert system",
        "safety and security system",
        "cctv with ai analytics",
        "access control system",
        "disaster management system",
        "business continuity system",
        "data center",
        "server room",
        "network operation center",
        "it helpdesk",
        "digital transformation office",
        "chief information officer",
        "chief digital officer",
        "digital innovation team"
      ],
      "responses": [
        "kampus dilengkapi wifi 10gbps di semua area 100 smart classroom data center tier 3 dan hpc untuk penelitian ai",
        "fasilitas digital mobile app terintegrasi cashless payment digital library 24 7 dan innovation lab dengan peralatan terkini"
      ],
      "context": [
        "infrastruktur"
      ],
      "entities": [
        "teknologi",
        "kapasitas",
        "akses",
        "lokasi"
      ],
      "follow_up": []
    },
    {
      "tag": "kesetaraan_gender",
      "original_patterns_count": 56,
      "processed_patterns_count": 56,
      "patterns_cleaned": [
        "kesetaraan gender di kampus",
        "gender equality policy",
        "women in stem program",
        "support for female students",
        "support for male students in non traditional field",
        "lgbtq support",
        "gender neutral toilet",
        "lactation room",
        "childcare facility",
        "parent support for student",
        "sexual harassment prevention",
        "gender based violence prevention",
        "consent education",
        "healthy relationship workshop",
        "gender bias training",
        "unconscious bias workshop",
        "inclusive language guide",
        "diversity and inclusion office",
        "women leadership program",
        "female faculty development",
        "gender research center",
        "women studies program",
        "men studies program",
        "gender and development program",
        "feminist theory course",
        "masculinity studies",
        "queer studies",
        "transgender support",
        "non binary student support",
        "intersectionality program",
        "disability and gender",
        "race and gender",
        "religion and gender",
        "class and gender",
        "gender pay gap research",
        "glass ceiling research",
        "women entrepreneurship support",
        "female founder network",
        "women in tech program",
        "women in engineering",
        "women in medicine",
        "women in law",
        "women in business",
        "women in academia",
        "men in nursing",
        "men in early childhood education",
        "men in social work",
        "gender stereotype challenge",
        "toxic masculinity discussion",
        "positive masculinity program",
        "feminism 101 workshop",
        "gender equality certification",
        "sdg 5 achievement in campus",
        "gender mainstreaming in curriculum",
        "gender responsive pedagogy",
        "inclusive teaching practice"
      ],
      "responses": [
        "kampus memiliki office of gender equality and diversity dengan program women in stem parental support lactation rooms di 15 lokasi dan training inklusivitas wajib untuk dosen",
        "untuk masalah terkait gender dan inklusivitas hubungi atau ext 7777 confidential"
      ],
      "context": [
        "nilai_kampus"
      ],
      "entities": [],
      "follow_up": [
        "kebijakan_inklusi",
        "laporan_insiden"
      ]
    },
    {
      "tag": "keberlanjutan",
      "original_patterns_count": 60,
      "processed_patterns_count": 60,
      "patterns_cleaned": [
        "keberlanjutan di kampus",
        "sustainable campus",
        "green campus initiative",
        "environmental policy",
        "carbon neutral campus",
        "renewable energy in campus",
        "solar panel installation",
        "rainwater harvesting",
        "waste management",
        "recycling program",
        "composting facility",
        "zero waste campaign",
        "plastic free campus",
        "single use plastic ban",
        "sustainable transportation",
        "bicycle friendly campus",
        "electric vehicle charging",
        "carpool program",
        "green building certification",
        "leed certified building",
        "energy efficient building",
        "water conservation",
        "green space preservation",
        "biodiversity in campus",
        "urban farming",
        "organic garden",
        "sustainable food",
        "vegetarian option in cafeteria",
        "local food sourcing",
        "fair trade products",
        "sustainable procurement",
        "green office program",
        "paperless office",
        "digital document system",
        "environmental education",
        "sustainability curriculum",
        "climate change course",
        "environmental science program",
        "sustainable development program",
        "circular economy research",
        "green technology research",
        "environmental impact assessment",
        "carbon footprint calculator",
        "sustainability report",
        "sdg implementation in campus",
        "united nations sdg program",
        "sustainability ranking",
        "green metric",
        "environmental audit",
        "sustainability committee",
        "student environmental club",
        "eco volunteer",
        "tree planting program",
        "clean up day",
        "earth day celebration",
        "world environment day",
        "climate strike support",
        "environmental activism",
        "sustainability internship",
        "green job opportunity"
      ],
      "responses": [
        "kampus kami berkomitmen menjadi carbon neutral pada 2030 saat ini 40 energi dari surya 80 limbah didaur ulang dan 100 gedung baru berstandar green building",
        "program keberlanjutan sepeda kampus gratis kantin zero waste urban farming dan mata kuliah wajib sustainability 101"
      ],
      "context": [
        "nilai_kampus"
      ],
      "entities": [
        "target",
        "pencapaian",
        "program",
        "partisipasi"
      ],
      "follow_up": []
    },
    {
      "tag": "bencana_alam",
      "original_patterns_count": 58,
      "processed_patterns_count": 58,
      "patterns_cleaned": [
        "kesiapsiagaan bencana di kampus",
        "disaster preparedness",
        "earthquake safety in campus",
        "flood prevention",
        "fire safety",
        "evacuation route",
        "emergency assembly point",
        "first aid training",
        "search and rescue team",
        "disaster response plan",
        "business continuity plan",
        "backup power generator",
        "emergency communication system",
        "early warning system",
        "tsunami evacuation drill",
        "earthquake drill",
        "fire drill",
        "active shooter drill",
        "emergency supplies",
        "disaster relief",
        "campus as emergency shelter",
        "volunteer for disaster response",
        "psychological first aid",
        "trauma counseling after disaster",
        "disaster risk reduction research",
        "climate adaptation research",
        "resilient infrastructure",
        "disaster resistant building",
        "flood control system",
        "drainage system",
        "landslide prevention",
        "volcano monitoring",
        "tsunami research",
        "earthquake engineering",
        "fire safety engineering",
        "structural safety",
        "emergency medicine training",
        "disaster nursing",
        "public health in disaster",
        "food security in disaster",
        "water security in disaster",
        "sanitation in emergency",
        "disaster management course",
        "humanitarian logistics",
        "refugee studies",
        "post disaster reconstruction",
        "community resilience",
        "indigenous knowledge for disaster",
        "disaster and gender",
        "disaster and disability",
        "disaster and children",
        "disaster and elderly",
        "animal rescue in disaster",
        "cultural heritage protection in disaster",
        "disaster insurance",
        "disaster fund",
        "international cooperation in disaster",
        "un collaboration for disaster"
      ],
      "responses": [
        "kampus memiliki disaster management center dengan sistem early warning tim sar terlatih shelter capacity 5000 orang dan pelatihan rutin untuk seluruh sivitas",
        "dalam keadaan darurat ikuti instruksi sirine evakuasi ke titik kumpulan dan pantau informasi melalui emergency univ ac id"
      ],
      "context": [
        "keselamatan"
      ],
      "entities": [],
      "follow_up": []
    },
    {
      "tag": "kesehatan_mental",
      "original_patterns_count": 60,
      "processed_patterns_count": 60,
      "patterns_cleaned": [
        "kesehatan mental mahasiswa",
        "mental health support",
        "stress management",
        "anxiety counseling",
        "depression treatment",
        "burnout prevention",
        "academic pressure coping",
        "time management for mental health",
        "mindfulness meditation",
        "yoga for stress relief",
        "sleep hygiene workshop",
        "nutrition for mental health",
        "exercise for mental health",
        "art therapy",
        "music therapy",
        "dance therapy",
        "pet therapy",
        "nature therapy",
        "peer support group",
        "buddy system",
        "crisis hotline",
        "suicide prevention",
        "self harm prevention",
        "eating disorder support",
        "substance abuse counseling",
        "addiction treatment",
        "trauma counseling",
        "ptsd support",
        "grief counseling",
        "relationship counseling",
        "family counseling",
        "career counseling for mental health",
        "financial stress counseling",
        "social anxiety support",
        "test anxiety support",
        "presentation anxiety",
        "public speaking fear",
        "perfectionism counseling",
        "procrastination help",
        "motivation problem",
        "adhd support",
        "autism spectrum support",
        "bipolar disorder support",
        "schizophrenia support",
        "personality disorder support",
        "mental health first aid training",
        "mental health awareness campaign",
        "stigma reduction program",
        "mental health screening",
        "psychological assessment",
        "psychiatric referral",
        "medication management",
        "hospitalization for mental health",
        "return to study after mental health leave",
        "mental health accommodation",
        "disability support for mental health",
        "mental health policy",
        "mental health day",
        "mental health in curriculum",
        "mental health research"
      ],
      "responses": [
        "counseling center buka 24 7 dengan hotline 1500 555 confidential layanan konseling individu kelompok crisis intervention workshop mindfulness dan referral ke psikiater",
        "jangan ragu mencari bantuan 1 dari 3 mahasiswa mengalami masalah mental itu normal chat anonim tersedia di mentalhealth univ ac id"
      ],
      "context": [
        "layanan_khusus"
      ],
      "entities": [],
      "follow_up": []
    },
    {
      "tag": "prestasi_non_akademik",
      "original_patterns_count": 62,
      "processed_patterns_count": 62,
      "patterns_cleaned": [
        "prestasi non akademik",
        "achievement in sports",
        "art competition award",
        "music competition",
        "dance competition",
        "theater competition",
        "debate championship",
        "model united nations award",
        "science olympiad",
        "math olympiad",
        "physics olympiad",
        "chemistry olympiad",
        "biology olympiad",
        "informatics olympiad",
        "robotics competition",
        "programming competition",
        "hackathon award",
        "business plan competition",
        "startup competition",
        "social innovation competition",
        "environmental competition",
        "sustainable development competition",
        "human rights competition",
        "moot court competition",
        "mock trial competition",
        "arbitration competition",
        "negotiation competition",
        "mediation competition",
        "public speaking competition",
        "poetry competition",
        "writing competition",
        "journalism competition",
        "photography competition",
        "film competition",
        "design competition",
        "architecture competition",
        "engineering competition",
        "medical competition",
        "nursing competition",
        "pharmacy competition",
        "dentistry competition",
        "veterinary competition",
        "agriculture competition",
        "fishery competition",
        "maritime competition",
        "aviation competition",
        "space competition",
        "defense competition",
        "leadership competition",
        "community service competition",
        "volunteer award",
        "social impact award",
        "entrepreneurship award",
        "innovation award",
        "creativity award",
        "research competition for undergraduate",
        "thesis competition",
        "publication competition",
        "patent competition",
        "technology competition",
        "invention competition",
        "discovery competition"
      ],
      "responses": [
        "mahasiswa kami telah memenangkan 500 kompetisi nasional internasional dalam 5 tahun terakhir dukungan pelatihan khusus pendanaan kompetisi dan konversi sks untuk prestasi",
        "untuk mendaftar kompetisi atau melaporkan prestasi hubungi student achievement center di"
      ],
      "context": [
        "pengakuan"
      ],
      "entities": [],
      "follow_up": [
        "pendaftaran_kompetisi",
        "beasiswa_prestasi"
      ]
    }
  ]
}